{
    "test@test.fr": [
        {
            "id": "b0aa76b5",
            "type": "deposit",
            "amount": 1000,
            "date": "2025-01-09T14:51:57.668978",
            "iban": null
        },
        {
            "id": "97ab3c65",
            "type": "deposit",
            "amount": 500,
            "date": "2025-01-09T15:12:27.075876",
            "iban": null
        },
        {
            "id": "873e2e55",
            "type": "withdraw",
            "amount": 2000,
            "date": "2025-01-09T15:13:59.057359",
            "iban": "FR7630006000011234567890189"
        },
        {
            "id": "247a6745",
            "type": "deposit",
            "amount": 2,
            "date": "2025-01-09T15:15:54.067971",
            "iban": null
        },
        {
            "id": "2b3b4cb0",
            "type": "withdraw",
            "amount": 123,
            "date": "2025-01-09T15:26:37.105156",
            "iban": "FR7630006000011234567890189"
        },
        {
            "id": "434c97ee",
            "type": "deposit",
            "amount": 1000000000,
            "date": "2025-01-09T16:00:25.277682",
            "iban": null
        },
        {
            "id": "a79a8096",
            "type": "withdraw",
            "amount": 19000,
            "date": "2025-01-09T16:01:16.333521",
            "iban": "FR7630006000011234567890189"
        }
    ]
}